{
  "id": "76ba7680-bf96-4203-8fba-b5be0d564442",
  "prevId": "33e17828-4494-48ab-abda-2c246ee825d3",
  "version": "7",
  "dialect": "postgresql",
  "tables": {
    "public.database_connections": {
      "name": "database_connections",
      "schema": "",
      "columns": {
        "id": {
          "name": "id",
          "type": "uuid",
          "primaryKey": true,
          "notNull": true,
          "default": "gen_random_uuid()"
        },
        "source": {
          "name": "source",
          "type": "text",
          "primaryKey": false,
          "notNull": true
        },
        "mode": {
          "name": "mode",
          "type": "db_mode",
          "typeSchema": "public",
          "primaryKey": false,
          "notNull": true
        },
        "db_name": {
          "name": "db_name",
          "type": "text",
          "primaryKey": false,
          "notNull": true
        },
        "db_credentials": {
          "name": "db_credentials",
          "type": "jsonb",
          "primaryKey": false,
          "notNull": true
        },
        "created_at": {
          "name": "created_at",
          "type": "timestamp",
          "primaryKey": false,
          "notNull": true,
          "default": "now()"
        },
        "updated_at": {
          "name": "updated_at",
          "type": "timestamp",
          "primaryKey": false,
          "notNull": true,
          "default": "now()"
        }
      },
      "indexes": {
        "uniq_dbname_per_source": {
          "name": "uniq_dbname_per_source",
          "columns": [
            {
              "expression": "source",
              "isExpression": false,
              "asc": true,
              "nulls": "last"
            },
            {
              "expression": "db_name",
              "isExpression": false,
              "asc": true,
              "nulls": "last"
            }
          ],
          "isUnique": true,
          "concurrently": false,
          "method": "btree",
          "with": {}
        }
      },
      "foreignKeys": {},
      "compositePrimaryKeys": {},
      "uniqueConstraints": {},
      "policies": {},
      "checkConstraints": {},
      "isRLSEnabled": false
    }
  },
  "enums": {
    "public.db_mode": {
      "name": "db_mode",
      "schema": "public",
      "values": [
        "url",
        "parameters"
      ]
    }
  },
  "schemas": {},
  "sequences": {},
  "roles": {},
  "policies": {},
  "views": {},
  "_meta": {
    "columns": {},
    "schemas": {},
    "tables": {}
  }
}